xj_user/__init__.py
xj_user/admin.py
xj_user/api2.py
xj_user/apps.py
xj_user/config[del].py
xj_user/models.py
xj_user/service_register.py
xj_user/urls.py
xj_user/validator.py
xj_user/views.py
xj_user/apis/__init__.py
xj_user/apis/user_add.py
xj_user/apis/user_apply_apis.py
xj_user/apis/user_cards_apis.py
xj_user/apis/user_contact_book.py
xj_user/apis/user_detail_info.py
xj_user/apis/user_edit.py
xj_user/apis/user_group.py
xj_user/apis/user_group_tree.py
xj_user/apis/user_info.py
xj_user/apis/user_list.py
xj_user/apis/user_login.py
xj_user/apis/user_login_main.py
xj_user/apis/user_login_short_message.py
xj_user/apis/user_login_wechat.py
xj_user/apis/user_login_wechat_app.py
xj_user/apis/user_password.py
xj_user/apis/user_permission.py
xj_user/apis/user_platform.py
xj_user/apis/user_register.py
xj_user/apis/user_relate_apis.py
xj_user/apis/user_sso_serve.py
xj_user/apis/user_statistics.py
xj_user/apis/user_subcompany_apis [del by sieyoo].py
xj_user/libs/__init__.py
xj_user/libs/jwt/__init__.py
xj_user/libs/jwt/exceptions.py
xj_user/libs/jwt/jwa.py
xj_user/libs/jwt/jwk.py
xj_user/libs/jwt/jwkset.py
xj_user/libs/jwt/jws.py
xj_user/libs/jwt/jwt.py
xj_user/libs/jwt/utils.py
xj_user/libs/pinyin/Mandarin.dat
xj_user/libs/pinyin/__init__.py
xj_user/libs/pinyin/_compat.py
xj_user/libs/pinyin/cedict.py
xj_user/libs/pinyin/cedict.txt.gz
xj_user/libs/pinyin/cmd.py
xj_user/libs/pinyin/pinyin.py
xj_user/management/__init__.py
xj_user/management/commands/__init__.py
xj_user/management/commands/user_apply_unit_test.py
xj_user/management/commands/user_test.py
xj_user/migrations/0001_initial.py
xj_user/migrations/0002_remove_detailinfo_register_ip_and_more.py
xj_user/migrations/0003_alter_baseinfo_uuid.py
xj_user/migrations/__init__.py
xj_user/script/__init__.py
xj_user/services/__init__.py
xj_user/services/contact_book.py
xj_user/services/login_service.py
xj_user/services/user_apply_services.py
xj_user/services/user_bank_service.py
xj_user/services/user_detail_info_service.py
xj_user-2.0.4.dist-info/METADATA
xj_user-2.0.4.dist-info/WHEEL
xj_user-2.0.4.dist-info/top_level.txt
xj_user-2.0.4.dist-info/RECORD
