Metadata-Version: 2.1
Name: xj-user
Version: 2.0.4
Summary: 用户模块
Home-page: UNKNOWN
Author: Sieyoo
Author-email: sieyoo@163.com
License: apache 3.0
Platform: UNKNOWN
Requires-Dist: requests
Requires-Dist: cryptography >=39.0.2
